mldsutils/__init__.py
mldsutils/base.py
mldsutils/imblearn-test.py
mldsutils/pipeline.py
mldsutils/classification/__init__.py
mldsutils/classification/_classifiers.py
mldsutils/metrics/__init__.py
mldsutils/metrics/_classification.py
mldsutils/metrics/_regression.py
mldsutils/preprocessing/__init__.py
mldsutils/preprocessing/_feature_selection.py
mldsutils/preprocessing/_outlier_elimination.py
mldsutils/preprocessing/_resample.py
mldsutils/regression/__init__.py
mldsutils/regression/_regressors.py
mldsutils/tests/__init__.py
mldsutils/tests/test_resampler.py
mldsutils/tests/test_scorer.py
mldsutils/tests/test_shrinkage_lda_classifier.py
mldsutils/tests/test_variable_selector.py
mldsutils-0.0.3.dist-info/LICENSE
mldsutils-0.0.3.dist-info/METADATA
mldsutils-0.0.3.dist-info/WHEEL
mldsutils-0.0.3.dist-info/top_level.txt
mldsutils-0.0.3.dist-info/RECORD
