Metadata-Version: 2.1
Name: mldsutils
Version: 0.0.3
Summary: A toolkit for various machine learning tasks.
Author-email: Baris Gün Sürmeli <baris.suermeli@th-owl.de>
Project-URL: Homepage, https://github.com/barisguns/MachineLearningUtils
Project-URL: Bug Tracker, https://github.com/barisguns/MachineLearningUtils/issues
Classifier: Programming Language :: Python :: 3
Classifier: License :: OSI Approved :: MIT License
Classifier: Operating System :: OS Independent
Requires-Python: >=3.7
License-File: LICENSE
